LICENSE
model_pool/__init__.py
model_pool/fetch_check_aux.py
model_pool/load_model.py
model_pool/model_pool.py
model_pool/model_s.py
model_pool-0.1.3.dist-info/LICENSE
model_pool-0.1.3.dist-info/WHEEL
model_pool-0.1.3.dist-info/METADATA
model_pool-0.1.3.dist-info/RECORD
