Metadata-Version: 2.1
Name: model-pool
Version: 0.1.3
Summary: pack_name descr 
Home-page: https://github.com/ffreemt/align-model-pool
License: MIT
Author: ffreemt
Requires-Python: >=3.7.9,<4.0.0
Classifier: License :: OSI Approved :: MIT License
Classifier: Programming Language :: Python :: 3
Classifier: Programming Language :: Python :: 3.10
Classifier: Programming Language :: Python :: 3.8
Classifier: Programming Language :: Python :: 3.9
Requires-Dist: alive-progress (>=2.3.1,<3.0.0)
Requires-Dist: huggingface-hub (>=0.4.0,<0.5.0)
Requires-Dist: icecream (>=2.1.1,<3.0.0)
Requires-Dist: install (>=1.3.5,<2.0.0)
Requires-Dist: joblib (>=1.1.0,<2.0.0)
Requires-Dist: logzero (>=1.7.0,<2.0.0)
Requires-Dist: sentence-transformers (>=2.2.0,<3.0.0)
Project-URL: Repository, https://github.com/ffreemt/align-model-pool
